pyslash/__init__.py
pyslash/client.py
pyslash/converters.py
pyslash/decorators.py
pyslash/utils.py
dpyslash-1.2.2.dist-info/LICENSE
dpyslash-1.2.2.dist-info/METADATA
dpyslash-1.2.2.dist-info/WHEEL
dpyslash-1.2.2.dist-info/top_level.txt
dpyslash-1.2.2.dist-info/RECORD
