Metadata-Version: 2.1
Name: dpyslash
Version: 1.2.2
Summary: Improves slash commands for Python
Home-page: https://github.com/starsflower/discordpy-slash-commands
Author: starsflower
License: MIT
Platform: UNKNOWN
Classifier: License :: OSI Approved :: MIT License
Classifier: Programming Language :: Python :: 3
License-File: LICENSE
Requires-Dist: discord.py (==1.6.*)
Requires-Dist: discord-py-slash-command (==1.1.*)
Requires-Dist: docstring-parser (==0.7.*)
